marvin0624/__init__.py
marvin0624/basics.py
marvin0624/sparse.py
marvin0624-0.1.0.dist-info/licenses/License
marvin0624-0.1.0.dist-info/METADATA
marvin0624-0.1.0.dist-info/WHEEL
marvin0624-0.1.0.dist-info/top_level.txt
marvin0624-0.1.0.dist-info/RECORD
