Metadata-Version: 2.4
Name: marvin0624
Version: 0.1.0
Summary: A small example Python library demonstrating packaging.
Author-email: Marvin <202522081036@mail.bnu.edu.cn>
License: MIT
Project-URL: Homepage, https://example.com/marvin0624
Project-URL: Source, https://github.com/yourname/marvin0624
Classifier: Programming Language :: Python :: 3
Classifier: License :: OSI Approved :: MIT License
Classifier: Operating System :: OS Independent
Requires-Python: >=3.8
License-File: License
Dynamic: license-file
